client/__init__.py
client/audio.py
client/executor.py
ivrs_client-0.1.1.dist-info/METADATA
ivrs_client-0.1.1.dist-info/WHEEL
ivrs_client-0.1.1.dist-info/license
ivrs_client-0.1.1.dist-info/top_level.txt
ivrs_client-0.1.1.dist-info/RECORD
