Metadata-Version: 2.1
Name: ivrs_client
Version: 0.1.1
Summary: Client Building for Intelligent Voice Response System
Author: Nana
Author-email: hukmonjikoladafa@gmail.com
Requires-Python: >=3.6
License-File: license
